{
  "id": "examples/basic-usage",
  "title": "Basic Usage Examples",
  "description": "Common patterns for using Foresight.",
  "source": "@site/docs/examples/basic-usage.md",
  "sourceDirName": "examples",
  "slug": "/examples/basic-usage",
  "permalink": "/foresight-mcp/docs/examples/basic-usage",
  "draft": false,
  "unlisted": false,
  "editUrl": "https://github.com/daggerstuff/foresight-mcp/tree/main/apps/docs/docs/examples/basic-usage.md",
  "tags": [],
  "version": "current",
  "frontMatter": {
    "sidebar_label": "Basic Usage",
    "title": "Basic Usage Examples"
  },
  "sidebar": "tutorialSidebar",
  "previous": {
    "title": "CLI Reference",
    "permalink": "/foresight-mcp/docs/api/cli-reference"
  },
  "next": {
    "title": "Event Hooks",
    "permalink": "/foresight-mcp/docs/examples/event-hooks"
  }
}